{
  "kakao": {
    "mon": [],
    "tue": [],
    "wed": [],
    "thu": [],
    "fri": [],
    "sat": [
      {
        "title": "No 재민 Zone",
        "url": "https://webtoon.kakao.com/content/No-재민-Zone/4728",
        "thumb": "https://kr-a.kakaopagecdn.com/P/C/4728/bg/2x/d2e77214-9fcd-479e-a5c1-412d14b79e30.webp",
        "platform": "kakao",
        "day": "sat",
        "dayLabel": "토"
      },
      {
        "title": "무장 무투전",
        "url": "https://webtoon.kakao.com/content/무장---무투전/4064",
        "thumb": "https://kr-a.kakaopagecdn.com/P/C/4064/bg/1x/ecf3fe28-fb76-4d8c-99df-175d92e36f39.webp",
        "platform": "kakao",
        "day": "sat",
        "dayLabel": "토"
      },
      {
        "title": "먹튀범 XX 일지 19세 완전판",
        "url": "https://webtoon.kakao.com/content/먹튀범-XX-일지-19세-완전판/4797",
        "thumb": "https://kr-a.kakaopagecdn.com/P/C/4797/bg/1x/0e893e3d-c12d-4a83-9f4a-2239ba41689c.webp",
        "platform": "kakao",
        "day": "sat",
        "dayLabel": "토"
      },
      {
        "title": "레드스톰 왕의 귀환",
        "url": "https://webtoon.kakao.com/content/레드스톰---왕의-귀환/823",
        "thumb": "https://kr-a.kakaopagecdn.com/P/C/823/bg/1x/6670f60b-0e62-4c36-ad8a-85cf50e31446.webp",
        "platform": "kakao",
        "day": "sat",
        "dayLabel": "토"
      },
      {
        "title": "검은머리 미군 대원수",
        "url": "https://webtoon.kakao.com/content/검은머리-미군-대원수/4772",
        "thumb": "https://kr-a.kakaopagecdn.com/P/C/4772/bg/1x/38564b4c-03e6-4b89-9780-d68e6caafa04.webp",
        "platform": "kakao",
        "day": "sat",
        "dayLabel": "토"
      },
      {
        "title": "나쁠수록 맛있다",
        "url": "https://webtoon.kakao.com/content/나쁠수록-맛있다/4767",
        "thumb": "https://kr-a.kakaopagecdn.com/P/C/4767/bg/1x/422682c7-c52b-4e29-8bf7-8318a4200d10.webp",
        "platform": "kakao",
        "day": "sat",
        "dayLabel": "토"
      },
      {
        "title": "여자인 걸 왜 모르지",
        "url": "https://webtoon.kakao.com/content/여자인-걸-왜-모르지/3185",
        "thumb": "https://kr-a.kakaopagecdn.com/P/C/3185/bg/1x/75a7a7b6-be39-43d5-af30-cded9b2315ab.webp",
        "platform": "kakao",
        "day": "sat",
        "dayLabel": "토"
      },
      {
        "title": "망나니 PD 아이돌로 살아남기",
        "url": "https://webtoon.kakao.com/content/망나니-PD-아이돌로-살아남기/4419",
        "thumb": "https://kr-a.kakaopagecdn.com/P/C/4419/bg/1x/6510b97c-56e1-4042-b050-c5288839db83.webp",
        "platform": "kakao",
        "day": "sat",
        "dayLabel": "토"
      },
      {
        "title": "흑표 가문의 설표 아기님",
        "url": "https://webtoon.kakao.com/content/흑표-가문의-설표-아기님/4380",
        "thumb": "https://kr-a.kakaopagecdn.com/P/C/4380/bg/1x/9f96f02b-3fbe-49fc-b186-d11b091c9403.webp",
        "platform": "kakao",
        "day": "sat",
        "dayLabel": "토"
      },
      {
        "title": "아무튼 로판 맞습니다",
        "url": "https://webtoon.kakao.com/content/아무튼-로판-맞습니다/4834",
        "thumb": "https://kr-a.kakaopagecdn.com/P/C/4834/bg/1x/e8799e0e-0a2f-40ee-b0b7-d963b7e20a57.webp",
        "platform": "kakao",
        "day": "sat",
        "dayLabel": "토"
      },
      {
        "title": "템빨",
        "url": "https://webtoon.kakao.com/content/템빨/2379",
        "thumb": "https://kr-a.kakaopagecdn.com/P/C/2379/bg/1x/f757986a-1c9c-4682-a7a3-743cc8ff30d8.webp",
        "platform": "kakao",
        "day": "sat",
        "dayLabel": "토"
      },
      {
        "title": "반지하셋방",
        "url": "https://webtoon.kakao.com/content/반지하셋방/1347",
        "thumb": "https://kr-a.kakaopagecdn.com/P/C/1347/bg/1x/ab4d90b4-1e89-4be1-91a1-3985a73b2e89.webp",
        "platform": "kakao",
        "day": "sat",
        "dayLabel": "토"
      },
      {
        "title": "얼어붙은 플레이어의 귀환",
        "url": "https://webtoon.kakao.com/content/얼어붙은-플레이어의-귀환/2463",
        "thumb": "https://kr-a.kakaopagecdn.com/P/C/2463/bg/1x/668a1846-a9f7-4e32-bfc4-deae542eb86e.webp",
        "platform": "kakao",
        "day": "sat",
        "dayLabel": "토"
      },
      {
        "title": "전학생은 먹고 싶어",
        "url": "https://webtoon.kakao.com/content/전학생은-먹고-싶어/4725",
        "thumb": "https://kr-a.kakaopagecdn.com/P/C/4725/bg/1x/cc1c33ff-44c4-46f2-9489-2ea5a421fc63.webp",
        "platform": "kakao",
        "day": "sat",
        "dayLabel": "토"
      },
      {
        "title": "로그인 무림",
        "url": "https://webtoon.kakao.com/content/로그인-무림/2384",
        "thumb": "https://kr-a.kakaopagecdn.com/P/C/2384/bg/1x/5d642bca-08e9-4a45-96de-745db4fc1f9a.webp",
        "platform": "kakao",
        "day": "sat",
        "dayLabel": "토"
      },
      {
        "title": "고추밭에서 만나요 19세 완전판",
        "url": "https://webtoon.kakao.com/content/고추밭에서-만나요-19세-완전판/4771",
        "thumb": "https://kr-a.kakaopagecdn.com/P/C/4771/bg/1x/7607a60c-ec47-4b25-8987-47c1d40c9e36.webp",
        "platform": "kakao",
        "day": "sat",
        "dayLabel": "토"
      },
      {
        "title": "칸나는 어떠한 결심을 했다",
        "url": "https://webtoon.kakao.com/content/칸나는-어떠한-결심을-했다/4786",
        "thumb": "https://kr-a.kakaopagecdn.com/P/C/4786/bg/1x/e2ad92e3-2198-4a4f-be6b-b1fefc7fec4a.webp",
        "platform": "kakao",
        "day": "sat",
        "dayLabel": "토"
      },
      {
        "title": "남주의 입양딸이 되었습니다",
        "url": "https://webtoon.kakao.com/content/남주의-입양딸이-되었습니다/2664",
        "thumb": "https://kr-a.kakaopagecdn.com/P/C/2664/bg/1x/8f874c2e-eb85-4a7c-a1c9-ac9564605298.webp",
        "platform": "kakao",
        "day": "sat",
        "dayLabel": "토"
      },
      {
        "title": "우리 오빠는 내가 지킨다",
        "url": "https://webtoon.kakao.com/content/우리-오빠는-내가-지킨다/4832",
        "thumb": "https://kr-a.kakaopagecdn.com/P/C/4832/bg/1x/32edf511-5ea6-45bd-b23f-b7a2a41cb5c5.webp",
        "platform": "kakao",
        "day": "sat",
        "dayLabel": "토"
      },
      {
        "title": "경성 란제리 의상실",
        "url": "https://webtoon.kakao.com/content/경성-란제리-의상실/4289",
        "thumb": "https://kr-a.kakaopagecdn.com/P/C/4289/bg/1x/5f8c0e3a-5c71-4c5d-8092-78ab9b83558f.webp",
        "platform": "kakao",
        "day": "sat",
        "dayLabel": "토"
      },
      {
        "title": "이 나라를 없앨 예정인데요",
        "url": "https://webtoon.kakao.com/content/이-나라를-없앨-예정인데요/4388",
        "thumb": "https://kr-a.kakaopagecdn.com/P/C/4388/bg/1x/bad9bf5d-70c7-456f-867c-74e7824f9321.webp",
        "platform": "kakao",
        "day": "sat",
        "dayLabel": "토"
      },
      {
        "title": "가짜 성녀인데 신들이 집착한다 19세 완전판",
        "url": "https://webtoon.kakao.com/content/가짜-성녀인데-신들이-집착한다-19세-완전판/4816",
        "thumb": "https://kr-a.kakaopagecdn.com/P/C/4816/bg/1x/3e05fcb9-fd45-4db1-9c2f-7016c6bfb7f6.webp",
        "platform": "kakao",
        "day": "sat",
        "dayLabel": "토"
      },
      {
        "title": "가짜를 위한 장소는 없다",
        "url": "https://webtoon.kakao.com/content/가짜를-위한-장소는-없다/3281",
        "thumb": "https://kr-a.kakaopagecdn.com/P/C/3281/bg/1x/c9f2a3b0-f10a-4e15-93d6-058c6e3ad729.webp",
        "platform": "kakao",
        "day": "sat",
        "dayLabel": "토"
      },
      {
        "title": "샤크",
        "url": "https://webtoon.kakao.com/content/샤크/2308",
        "thumb": "https://kr-a.kakaopagecdn.com/P/C/2308/bg/1x/18ab4143-92c6-4f2e-8372-513cd7c567e7.webp",
        "platform": "kakao",
        "day": "sat",
        "dayLabel": "토"
      },
      {
        "title": "환생의 정석",
        "url": "https://webtoon.kakao.com/content/환생의-정석/3019",
        "thumb": "https://kr-a.kakaopagecdn.com/P/C/3019/bg/1x/63536973-4c8f-4084-a99f-21751f2fa0f0.webp",
        "platform": "kakao",
        "day": "sat",
        "dayLabel": "토"
      },
      {
        "title": "짝사랑 맞선 19세 완전판",
        "url": "https://webtoon.kakao.com/content/짝사랑-맞선-19세-완전판/4529",
        "thumb": "https://kr-a.kakaopagecdn.com/P/C/4529/bg/1x/43e17f18-d579-4529-bef2-15e42e49ebdc.webp",
        "platform": "kakao",
        "day": "sat",
        "dayLabel": "토"
      },
      {
        "title": "악마의 사랑을 받는 딸이래요",
        "url": "https://webtoon.kakao.com/content/악마의-사랑을-받는-딸이래요/3114",
        "thumb": "https://kr-a.kakaopagecdn.com/P/C/3114/bg/1x/977ec844-1e53-4ca8-820e-e6524470f3f4.webp",
        "platform": "kakao",
        "day": "sat",
        "dayLabel": "토"
      },
      {
        "title": "재워주는 사이",
        "url": "https://webtoon.kakao.com/content/재워주는-사이/2986",
        "thumb": "https://kr-a.kakaopagecdn.com/P/C/2986/bg/1x/4fe84b44-6396-4d6b-b292-70c26137d254.webp",
        "platform": "kakao",
        "day": "sat",
        "dayLabel": "토"
      },
      {
        "title": "의원 다시 살다",
        "url": "https://webtoon.kakao.com/content/의원-다시-살다/2440",
        "thumb": "https://kr-a.kakaopagecdn.com/P/C/2440/bg/1x/2247b3cf-33af-44fc-b657-8b7015be4f17.webp",
        "platform": "kakao",
        "day": "sat",
        "dayLabel": "토"
      },
      {
        "title": "쪽쪽이를 주세요",
        "url": "https://webtoon.kakao.com/content/쪽쪽이를-주세요/2816",
        "thumb": "https://kr-a.kakaopagecdn.com/P/C/2816/bg/1x/ba2f7c04-bfa8-4b9e-9c6e-bdca57191906.webp",
        "platform": "kakao",
        "day": "sat",
        "dayLabel": "토"
      },
      {
        "title": "창귀무쌍",
        "url": "https://webtoon.kakao.com/content/창귀무쌍/4660",
        "thumb": "https://kr-a.kakaopagecdn.com/P/C/4660/bg/1x/60729ebd-c4e0-453d-a64a-5b848995e620.webp",
        "platform": "kakao",
        "day": "sat",
        "dayLabel": "토"
      },
      {
        "title": "천하제일 무공교관",
        "url": "https://webtoon.kakao.com/content/천하제일-무공교관/4352",
        "thumb": "https://kr-a.kakaopagecdn.com/P/C/4352/bg/1x/fe7261ee-36a4-48d9-b363-4bbb44f5ad4a.webp",
        "platform": "kakao",
        "day": "sat",
        "dayLabel": "토"
      },
      {
        "title": "가짜 성녀인데 신들이 집착한다",
        "url": "https://webtoon.kakao.com/content/가짜-성녀인데-신들이-집착한다/3403",
        "thumb": "https://kr-a.kakaopagecdn.com/P/C/3403/bg/1x/e4945a3f-d79c-4db5-a3a0-66c1a87355e0.webp",
        "platform": "kakao",
        "day": "sat",
        "dayLabel": "토"
      },
      {
        "title": "던전 견문록",
        "url": "https://webtoon.kakao.com/content/던전-견문록/3190",
        "thumb": "https://kr-a.kakaopagecdn.com/P/C/3190/bg/1x/502ad009-f6a5-4c95-a9fe-79738da5b227.webp",
        "platform": "kakao",
        "day": "sat",
        "dayLabel": "토"
      },
      {
        "title": "어떤 계모님의 메르헨",
        "url": "https://webtoon.kakao.com/content/어떤-계모님의-메르헨/4478",
        "thumb": "https://kr-a.kakaopagecdn.com/P/C/4478/bg/1x/886a4e6a-9379-4a02-8f46-d7589ba33ad4.webp",
        "platform": "kakao",
        "day": "sat",
        "dayLabel": "토"
      },
      {
        "title": "부르다가 내가 죽을 여자뮤지션",
        "url": "https://webtoon.kakao.com/content/부르다가-내가-죽을-여자뮤지션/3510",
        "thumb": "https://kr-a.kakaopagecdn.com/P/C/3510/bg/1x/93b1ce62-1241-40ee-ba61-cbd97f42fbbd.webp",
        "platform": "kakao",
        "day": "sat",
        "dayLabel": "토"
      },
      {
        "title": "천재 대장장이의 게임",
        "url": "https://webtoon.kakao.com/content/천재-대장장이의-게임/4639",
        "thumb": "https://kr-a.kakaopagecdn.com/P/C/4639/bg/1x/9378ac1c-fc42-469e-b856-eb198a2a841e.webp",
        "platform": "kakao",
        "day": "sat",
        "dayLabel": "토"
      },
      {
        "title": "육아 예능 찍는 막내님은 사랑스러워",
        "url": "https://webtoon.kakao.com/content/육아-예능-찍는-막내님은-사랑스러워/4831",
        "thumb": "https://kr-a.kakaopagecdn.com/P/C/4831/bg/1x/8e2f6508-b919-4d4a-a5d5-59f0d68c8595.webp",
        "platform": "kakao",
        "day": "sat",
        "dayLabel": "토"
      },
      {
        "title": "정령왕 엘퀴네스",
        "url": "https://webtoon.kakao.com/content/정령왕-엘퀴네스/2309",
        "thumb": "https://kr-a.kakaopagecdn.com/P/C/2309/bg/1x/b180bf22-486a-4de0-b07e-7ee998a7546c.webp",
        "platform": "kakao",
        "day": "sat",
        "dayLabel": "토"
      },
      {
        "title": "회귀한 천재 플레이어의 신화급 무기창조",
        "url": "https://webtoon.kakao.com/content/회귀한-천재-플레이어의-신화급-무기창조/4379",
        "thumb": "https://kr-a.kakaopagecdn.com/P/C/4379/bg/1x/0defc9b5-924c-4bd4-b276-8960d77d47f0.webp",
        "platform": "kakao",
        "day": "sat",
        "dayLabel": "토"
      },
      {
        "title": "이물질은 나였다",
        "url": "https://webtoon.kakao.com/content/이물질은-나였다/4311",
        "thumb": "https://kr-a.kakaopagecdn.com/P/C/4311/bg/1x/1850dcec-ea4d-433d-8c77-6e2caa02cc99.webp",
        "platform": "kakao",
        "day": "sat",
        "dayLabel": "토"
      },
      {
        "title": "칠흑이 삼킨 여름",
        "url": "https://webtoon.kakao.com/content/칠흑이-삼킨-여름/4500",
        "thumb": "https://kr-a.kakaopagecdn.com/P/C/4500/bg/1x/409551b9-fe7c-427d-a753-83f45b66233c.webp",
        "platform": "kakao",
        "day": "sat",
        "dayLabel": "토"
      },
      {
        "title": "회귀 경찰의 리셋 라이프",
        "url": "https://webtoon.kakao.com/content/회귀-경찰의-리셋-라이프/3284",
        "thumb": "https://kr-a.kakaopagecdn.com/P/C/3284/bg/1x/dd6465ba-492c-486f-a4e3-6728def4c4cc.webp",
        "platform": "kakao",
        "day": "sat",
        "dayLabel": "토"
      },
      {
        "title": "보스 몹답게 행동하세요 스왈로우 씨",
        "url": "https://webtoon.kakao.com/content/보스-몹답게-행동하세요-스왈로우-씨/3892",
        "thumb": "https://kr-a.kakaopagecdn.com/P/C/3892/bg/1x/a23daf30-b2be-4677-a0ac-12326e4a82a9.webp",
        "platform": "kakao",
        "day": "sat",
        "dayLabel": "토"
      },
      {
        "title": "악당을 납치한 5살 스파이입니다",
        "url": "https://webtoon.kakao.com/content/악당을-납치한-5살-스파이입니다/4829",
        "thumb": "https://kr-a.kakaopagecdn.com/P/C/4829/bg/1x/87505751-8156-43b6-a8b8-d138fd32cf22.webp",
        "platform": "kakao",
        "day": "sat",
        "dayLabel": "토"
      },
      {
        "title": "악녀의 맞선남이 너무 완벽하다",
        "url": "https://webtoon.kakao.com/content/악녀의-맞선남이-너무-완벽하다/3652",
        "thumb": "https://kr-a.kakaopagecdn.com/P/C/3652/bg/1x/8521a780-d22b-4fd2-acb5-4f070679f9df.webp",
        "platform": "kakao",
        "day": "sat",
        "dayLabel": "토"
      },
      {
        "title": "집착은 다정하고 집요하게 19세 완전판",
        "url": "https://webtoon.kakao.com/content/집착은-다정하고-집요하게-19세-완전판/4319",
        "thumb": "https://kr-a.kakaopagecdn.com/P/C/4319/bg/1x/0e41b496-4bb6-45d0-a085-70c9cd20ebba.webp",
        "platform": "kakao",
        "day": "sat",
        "dayLabel": "토"
      },
      {
        "title": "여주의 첫사랑을 빼앗아 버렸다",
        "url": "https://webtoon.kakao.com/content/여주의-첫사랑을-빼앗아-버렸다/3664",
        "thumb": "https://kr-a.kakaopagecdn.com/P/C/3664/bg/1x/77620059-a5d8-48e3-8099-43a86a749ff0.webp",
        "platform": "kakao",
        "day": "sat",
        "dayLabel": "토"
      },
      {
        "title": "복수는 이렇게 하는 거다",
        "url": "https://webtoon.kakao.com/content/복수는-이렇게-하는-거다/4737",
        "thumb": "https://kr-a.kakaopagecdn.com/P/C/4737/bg/1x/ed93a388-28bc-4322-bbda-eab07a8ce322.webp",
        "platform": "kakao",
        "day": "sat",
        "dayLabel": "토"
      },
      {
        "title": "전남편을 삭제합니다",
        "url": "https://webtoon.kakao.com/content/전남편을-삭제합니다/4569",
        "thumb": "https://kr-a.kakaopagecdn.com/P/C/4569/bg/1x/5562ee25-abc1-4436-851b-2c18debd2ec2.webp",
        "platform": "kakao",
        "day": "sat",
        "dayLabel": "토"
      },
      {
        "title": "시한부 흑막이 내 파혼을 후원한다",
        "url": "https://webtoon.kakao.com/content/시한부-흑막이-내-파혼을-후원한다/4163",
        "thumb": "https://kr-a.kakaopagecdn.com/P/C/4163/bg/1x/5fea8f09-4a84-4722-aa65-0912cd844b87.webp",
        "platform": "kakao",
        "day": "sat",
        "dayLabel": "토"
      },
      {
        "title": "공포게임 메이드로 살아남기",
        "url": "https://webtoon.kakao.com/content/공포게임-메이드로-살아남기/3654",
        "thumb": "https://kr-a.kakaopagecdn.com/P/C/3654/bg/1x/ea95635a-3899-4938-99f3-7060b89dfa09.webp",
        "platform": "kakao",
        "day": "sat",
        "dayLabel": "토"
      },
      {
        "title": "헬무트",
        "url": "https://webtoon.kakao.com/content/헬무트/3217",
        "thumb": "https://kr-a.kakaopagecdn.com/P/C/3217/bg/1x/3939cfd3-f9a4-4e4b-b58b-890468247789.webp",
        "platform": "kakao",
        "day": "sat",
        "dayLabel": "토"
      },
      {
        "title": "스킬빨로 레벨업",
        "url": "https://webtoon.kakao.com/content/스킬빨로-레벨업/3540",
        "thumb": "https://kr-a.kakaopagecdn.com/P/C/3540/bg/1x/bd319aff-d1e0-4ac9-96a6-d5e78078e995.webp",
        "platform": "kakao",
        "day": "sat",
        "dayLabel": "토"
      },
      {
        "title": "첫사랑의 온도",
        "url": "https://webtoon.kakao.com/content/첫사랑의-온도/4727",
        "thumb": "https://kr-a.kakaopagecdn.com/P/C/4727/bg/1x/6426fc4c-5bf9-4bb7-ad4e-9d659b6224b9.webp",
        "platform": "kakao",
        "day": "sat",
        "dayLabel": "토"
      },
      {
        "title": "공작님 제발 좀 망하세요",
        "url": "https://webtoon.kakao.com/content/공작님-제발-좀-망하세요/3951",
        "thumb": "https://kr-a.kakaopagecdn.com/P/C/3951/bg/1x/ec32422b-8aee-44a2-b702-28847f184b8a.webp",
        "platform": "kakao",
        "day": "sat",
        "dayLabel": "토"
      },
      {
        "title": "악녀는 대공을 사로잡았다",
        "url": "https://webtoon.kakao.com/content/악녀는-대공을-사로잡았다/3941",
        "thumb": "https://kr-a.kakaopagecdn.com/P/C/3941/bg/1x/8e9f5617-67ee-42d9-a020-526d2cfcbb20.webp",
        "platform": "kakao",
        "day": "sat",
        "dayLabel": "토"
      },
      {
        "title": "환생마신전",
        "url": "https://webtoon.kakao.com/content/환생마신전/4335",
        "thumb": "https://kr-a.kakaopagecdn.com/P/C/4335/bg/1x/c15dfc79-fc73-499f-b6dc-74f97e62b2fc.webp",
        "platform": "kakao",
        "day": "sat",
        "dayLabel": "토"
      },
      {
        "title": "악당은 살고 싶다",
        "url": "https://webtoon.kakao.com/content/악당은-살고-싶다/4414",
        "thumb": "https://kr-a.kakaopagecdn.com/P/C/4414/bg/1x/899ba1fe-4947-4e59-a49a-3f00b894e6b3.webp",
        "platform": "kakao",
        "day": "sat",
        "dayLabel": "토"
      },
      {
        "title": "귀짤 로맨스",
        "url": "https://webtoon.kakao.com/content/귀짤-로맨스/3371",
        "thumb": "https://kr-a.kakaopagecdn.com/P/C/3371/bg/1x/0874c6e8-de8a-4d6c-b61f-317a79b5365d.webp",
        "platform": "kakao",
        "day": "sat",
        "dayLabel": "토"
      },
      {
        "title": "사천당가의 시비로 살아남기",
        "url": "https://webtoon.kakao.com/content/사천당가의-시비로-살아남기/4678",
        "thumb": "https://kr-a.kakaopagecdn.com/P/C/4678/bg/1x/5e82af4b-f140-4335-92ec-0f4e11faa258.webp",
        "platform": "kakao",
        "day": "sat",
        "dayLabel": "토"
      },
      {
        "title": "세계관 최강자들이 내게 집착한다",
        "url": "https://webtoon.kakao.com/content/세계관-최강자들이-내게-집착한다/3261",
        "thumb": "https://kr-a.kakaopagecdn.com/P/C/3261/bg/1x/7714d844-a900-4a75-be20-ff0eee4dd49d.webp",
        "platform": "kakao",
        "day": "sat",
        "dayLabel": "토"
      },
      {
        "title": "괴물 황녀님",
        "url": "https://webtoon.kakao.com/content/괴물-황녀님/3392",
        "thumb": "https://kr-a.kakaopagecdn.com/P/C/3392/bg/1x/78902e26-2d9e-48a2-95c6-745d262d22c3.webp",
        "platform": "kakao",
        "day": "sat",
        "dayLabel": "토"
      },
      {
        "title": "먼지 덩어리 짱덕",
        "url": "https://webtoon.kakao.com/content/먼지-덩어리-짱덕/4288",
        "thumb": "https://kr-a.kakaopagecdn.com/P/C/4288/bg/1x/2a67eaa7-e75b-4247-8891-221070b9f4d9.webp",
        "platform": "kakao",
        "day": "sat",
        "dayLabel": "토"
      },
      {
        "title": "미친 남주들과 같은 반이 되었다",
        "url": "https://webtoon.kakao.com/content/미친-남주들과-같은-반이-되었다/4353",
        "thumb": "https://kr-a.kakaopagecdn.com/P/C/4353/bg/1x/839bf06c-7f3e-484d-9d83-5945a27404e9.webp",
        "platform": "kakao",
        "day": "sat",
        "dayLabel": "토"
      },
      {
        "title": "결혼하지 않으면 죽습니다",
        "url": "https://webtoon.kakao.com/content/결혼하지-않으면-죽습니다/4598",
        "thumb": "https://kr-a.kakaopagecdn.com/P/C/4598/bg/1x/e3c8f78e-6efd-4e78-9e92-b69e986124f2.webp",
        "platform": "kakao",
        "day": "sat",
        "dayLabel": "토"
      },
      {
        "title": "키워준 은혜를 집착으로 갚으시다니요",
        "url": "https://webtoon.kakao.com/content/키워준-은혜를-집착으로-갚으시다니요/4231",
        "thumb": "https://kr-a.kakaopagecdn.com/P/C/4231/bg/1x/130c9430-920d-4f68-9f9a-13a4b07ff862.webp",
        "platform": "kakao",
        "day": "sat",
        "dayLabel": "토"
      },
      {
        "title": "엔딩인 줄 알고 돌아왔더니 장르가 바뀜",
        "url": "https://webtoon.kakao.com/content/엔딩인-줄-알고-돌아왔더니-장르가-바뀜/4776",
        "thumb": "https://kr-a.kakaopagecdn.com/P/C/4776/bg/1x/7d926505-8e18-42e9-94e1-51a14e7f6122.webp",
        "platform": "kakao",
        "day": "sat",
        "dayLabel": "토"
      },
      {
        "title": "던전 안 푸드 트럭 사장님",
        "url": "https://webtoon.kakao.com/content/던전-안-푸드-트럭-사장님/4119",
        "thumb": "https://kr-a.kakaopagecdn.com/P/C/4119/bg/1x/81075796-37ec-4250-8048-c5c798ecac55.webp",
        "platform": "kakao",
        "day": "sat",
        "dayLabel": "토"
      },
      {
        "title": "내 소원은 침대 두 개 19세 완전판",
        "url": "https://webtoon.kakao.com/content/내-소원은-침대-두-개-19세-완전판/4377",
        "thumb": "https://kr-a.kakaopagecdn.com/P/C/4377/bg/1x/583ae888-d8df-42d6-9bd3-54df8159c6a1.webp",
        "platform": "kakao",
        "day": "sat",
        "dayLabel": "토"
      },
      {
        "title": "나를 죽인 황제의 딸로 살아남는 방법",
        "url": "https://webtoon.kakao.com/content/나를-죽인-황제의-딸로-살아남는-방법/4589",
        "thumb": "https://kr-a.kakaopagecdn.com/P/C/4589/bg/1x/5c2e79be-5c1f-4992-9e26-e410fc23b95c.webp",
        "platform": "kakao",
        "day": "sat",
        "dayLabel": "토"
      },
      {
        "title": "끝이 아닌 시작",
        "url": "https://webtoon.kakao.com/content/끝이-아닌-시작/3162",
        "thumb": "https://kr-a.kakaopagecdn.com/P/C/3162/bg/1x/1ec72b65-0daa-4c60-ab10-0f1fbfe03f2f.webp",
        "platform": "kakao",
        "day": "sat",
        "dayLabel": "토"
      },
      {
        "title": "곱게 키운 악당들",
        "url": "https://webtoon.kakao.com/content/곱게-키운-악당들/3026",
        "thumb": "https://kr-a.kakaopagecdn.com/P/C/3026/bg/1x/c68c1c67-d0f5-49c0-b5c8-25112364e0e6.webp",
        "platform": "kakao",
        "day": "sat",
        "dayLabel": "토"
      },
      {
        "title": "S급 헌터는 악역 공녀가 되기 싫습니다",
        "url": "https://webtoon.kakao.com/content/S급-헌터는-악역-공녀가-되기-싫습니다/3944",
        "thumb": "https://kr-a.kakaopagecdn.com/P/C/3944/bg/1x/af2292b9-062a-4b36-bb40-b8ae9b71438e.webp",
        "platform": "kakao",
        "day": "sat",
        "dayLabel": "토"
      },
      {
        "title": "너에게 하고 싶은 말",
        "url": "https://webtoon.kakao.com/content/너에게-하고-싶은-말/4784",
        "thumb": "https://kr-a.kakaopagecdn.com/P/C/4784/bg/1x/b0d418fb-1add-482f-9650-1c7516fb7235.webp",
        "platform": "kakao",
        "day": "sat",
        "dayLabel": "토"
      },
      {
        "title": "붉은 달밤의 끝자락에서",
        "url": "https://webtoon.kakao.com/content/붉은-달밤의-끝자락에서/4695",
        "thumb": "https://kr-a.kakaopagecdn.com/P/C/4695/bg/1x/9d92d99a-82e0-4f48-9d89-d6818f5966f8.webp",
        "platform": "kakao",
        "day": "sat",
        "dayLabel": "토"
      },
      {
        "title": "무공으로 레벨업하는 마왕님",
        "url": "https://webtoon.kakao.com/content/무공으로-레벨업하는-마왕님/3090",
        "thumb": "https://kr-a.kakaopagecdn.com/P/C/3090/bg/1x/9e434ff1-f143-4c2f-ab46-be473037a566.webp",
        "platform": "kakao",
        "day": "sat",
        "dayLabel": "토"
      },
      {
        "title": "시어머니지만 고부 갈등은 싫습니다",
        "url": "https://webtoon.kakao.com/content/시어머니지만-고부-갈등은-싫습니다/4421",
        "thumb": "https://kr-a.kakaopagecdn.com/P/C/4421/bg/1x/39b94127-7ada-4a53-97f0-29ca3911eb82.webp",
        "platform": "kakao",
        "day": "sat",
        "dayLabel": "토"
      },
      {
        "title": "유니유니툰",
        "url": "https://webtoon.kakao.com/content/유니유니툰/4624",
        "thumb": "https://kr-a.kakaopagecdn.com/P/C/4624/bg/1x/209fe210-bb69-41a2-9022-251a475b97c2.webp",
        "platform": "kakao",
        "day": "sat",
        "dayLabel": "토"
      },
      {
        "title": "31번째 말은 게임판을 뒤엎는다",
        "url": "https://webtoon.kakao.com/content/31번째-말은-게임판을-뒤엎는다/3603",
        "thumb": "https://kr-a.kakaopagecdn.com/P/C/3603/bg/1x/d5a7f207-758c-4d24-bfc9-c52a946a443a.webp",
        "platform": "kakao",
        "day": "sat",
        "dayLabel": "토"
      },
      {
        "title": "공작가에는 미친개가 산다",
        "url": "https://webtoon.kakao.com/content/공작가에는-미친개가-산다/4611",
        "thumb": "https://kr-a.kakaopagecdn.com/P/C/4611/bg/1x/bcd32532-079f-4779-beb2-76521961d5d3.webp",
        "platform": "kakao",
        "day": "sat",
        "dayLabel": "토"
      },
      {
        "title": "곧 망할 가문의 계약직 딸이 되었다",
        "url": "https://webtoon.kakao.com/content/곧-망할-가문의-계약직-딸이-되었다/4057",
        "thumb": "https://kr-a.kakaopagecdn.com/P/C/4057/bg/1x/ce7eb6fb-e358-4bca-9f1e-a584d068329f.webp",
        "platform": "kakao",
        "day": "sat",
        "dayLabel": "토"
      },
      {
        "title": "내 아이가 분명해",
        "url": "https://webtoon.kakao.com/content/내-아이가-분명해/3420",
        "thumb": "https://kr-a.kakaopagecdn.com/P/C/3420/bg/1x/8bcdda1e-c906-40da-8ee9-0b610dddaae3.webp",
        "platform": "kakao",
        "day": "sat",
        "dayLabel": "토"
      },
      {
        "title": "이혼당할 준비 완료했습니다",
        "url": "https://webtoon.kakao.com/content/이혼당할-준비-완료했습니다/4450",
        "thumb": "https://kr-a.kakaopagecdn.com/P/C/4450/bg/1x/66c3e0b5-c978-4367-b3a3-2fce581b2b2e.webp",
        "platform": "kakao",
        "day": "sat",
        "dayLabel": "토"
      },
      {
        "title": "오컬트 로맨틱 코미디 19세 완전판",
        "url": "https://webtoon.kakao.com/content/오컬트-로맨틱-코미디-19세-완전판/4530",
        "thumb": "https://kr-a.kakaopagecdn.com/P/C/4530/bg/1x/0323e676-8ad9-458e-819f-44b5b31fddde.webp",
        "platform": "kakao",
        "day": "sat",
        "dayLabel": "토"
      },
      {
        "title": "에보니",
        "url": "https://webtoon.kakao.com/content/에보니/2348",
        "thumb": "https://kr-a.kakaopagecdn.com/P/C/2348/bg/1x/12851379-7e73-4e17-9cfc-ccea7d1c8a42.webp",
        "platform": "kakao",
        "day": "sat",
        "dayLabel": "토"
      },
      {
        "title": "블러드레인 제로",
        "url": "https://webtoon.kakao.com/content/블러드레인-제로/4690",
        "thumb": "https://kr-a.kakaopagecdn.com/P/C/4690/bg/1x/54d43b03-091f-47b7-ac2b-3b6137179c50.webp",
        "platform": "kakao",
        "day": "sat",
        "dayLabel": "토"
      },
      {
        "title": "병약한 아빠를 간호했을 뿐인데",
        "url": "https://webtoon.kakao.com/content/병약한-아빠를-간호했을-뿐인데/4076",
        "thumb": "https://kr-a.kakaopagecdn.com/P/C/4076/bg/1x/fc20f196-bbeb-4750-a6db-668cd54bb748.webp",
        "platform": "kakao",
        "day": "sat",
        "dayLabel": "토"
      },
      {
        "title": "패륜 공작가에는 가정 교육이 필요하다",
        "url": "https://webtoon.kakao.com/content/패륜-공작가에는-가정-교육이-필요하다/4252",
        "thumb": "https://kr-a.kakaopagecdn.com/P/C/4252/bg/1x/56456b21-c65e-426d-890c-ca0b727d2b6d.webp",
        "platform": "kakao",
        "day": "sat",
        "dayLabel": "토"
      },
      {
        "title": "하백의 신부 2",
        "url": "https://webtoon.kakao.com/content/하백의-신부-2/4680",
        "thumb": "https://kr-a.kakaopagecdn.com/P/C/4680/bg/1x/7b92faf7-63f9-4608-bb38-d83804526a59.webp",
        "platform": "kakao",
        "day": "sat",
        "dayLabel": "토"
      },
      {
        "title": "귀환자의 히든 공략 스트리밍",
        "url": "https://webtoon.kakao.com/content/귀환자의-히든-공략-스트리밍/4788",
        "thumb": "https://kr-a.kakaopagecdn.com/P/C/4788/bg/1x/12cee500-d933-49f7-801d-2d8e2efb2b74.webp",
        "platform": "kakao",
        "day": "sat",
        "dayLabel": "토"
      },
      {
        "title": "만렙부터 레벨업",
        "url": "https://webtoon.kakao.com/content/만렙부터-레벨업/2651",
        "thumb": "https://kr-a.kakaopagecdn.com/P/C/2651/bg/1x/7453c049-27e9-4a89-9823-2090358d760c.webp",
        "platform": "kakao",
        "day": "sat",
        "dayLabel": "토"
      },
      {
        "title": "집착은 다정하고 집요하게",
        "url": "https://webtoon.kakao.com/content/집착은-다정하고-집요하게/4039",
        "thumb": "https://kr-a.kakaopagecdn.com/P/C/4039/bg/1x/b8731c9d-6be1-433a-82e6-5b307f69e759.webp",
        "platform": "kakao",
        "day": "sat",
        "dayLabel": "토"
      },
      {
        "title": "엔딩메이커",
        "url": "https://webtoon.kakao.com/content/엔딩메이커/2950",
        "thumb": "https://kr-a.kakaopagecdn.com/P/C/2950/bg/1x/968ce4d3-7c66-47f1-a052-9dec6acb39dc.webp",
        "platform": "kakao",
        "day": "sat",
        "dayLabel": "토"
      },
      {
        "title": "부기영화",
        "url": "https://webtoon.kakao.com/content/부기영화/2343",
        "thumb": "https://kr-a.kakaopagecdn.com/P/C/2343/bg/1x/48a30112-8a3c-400e-ad00-096cc5852d99.webp",
        "platform": "kakao",
        "day": "sat",
        "dayLabel": "토"
      },
      {
        "title": "딸이 귀엽고 남편이 멋짐",
        "url": "https://webtoon.kakao.com/content/딸이-귀엽고-남편이-멋짐/4751",
        "thumb": "https://kr-a.kakaopagecdn.com/P/C/4751/bg/1x/990c0cd7-cf41-43db-b628-8c2aa08c8b40.webp",
        "platform": "kakao",
        "day": "sat",
        "dayLabel": "토"
      },
      {
        "title": "용사 동생은 아카데미 고인물",
        "url": "https://webtoon.kakao.com/content/용사-동생은-아카데미-고인물/3342",
        "thumb": "https://kr-a.kakaopagecdn.com/P/C/3342/bg/1x/d16cdcb9-f2b9-4e10-911f-55541071c68d.webp",
        "platform": "kakao",
        "day": "sat",
        "dayLabel": "토"
      },
      {
        "title": "무림맹주 막내제자",
        "url": "https://webtoon.kakao.com/content/무림맹주-막내제자/4267",
        "thumb": "https://kr-a.kakaopagecdn.com/P/C/4267/bg/1x/509537cf-8a0f-4ec5-97da-4709da45fb27.webp",
        "platform": "kakao",
        "day": "sat",
        "dayLabel": "토"
      },
      {
        "title": "테이밍 마스터",
        "url": "https://webtoon.kakao.com/content/테이밍-마스터/2433",
        "thumb": "https://kr-a.kakaopagecdn.com/P/C/2433/bg/1x/2b350d33-d930-43c6-b02d-c72784add0da.webp",
        "platform": "kakao",
        "day": "sat",
        "dayLabel": "토"
      },
      {
        "title": "나 홀로 로그인",
        "url": "https://webtoon.kakao.com/content/나-홀로-로그인/2366",
        "thumb": "https://kr-a.kakaopagecdn.com/P/C/2366/bg/1x/5c3a73e1-c7dd-4d0b-bc05-1aa5e0a81bff.webp",
        "platform": "kakao",
        "day": "sat",
        "dayLabel": "토"
      },
      {
        "title": "엄마는 또 처음이라",
        "url": "https://webtoon.kakao.com/content/엄마는-또-처음이라/4520",
        "thumb": "https://kr-a.kakaopagecdn.com/P/C/4520/bg/1x/1b32df6e-b2ee-482e-9374-1853eec8e27e.webp",
        "platform": "kakao",
        "day": "sat",
        "dayLabel": "토"
      },
      {
        "title": "책빙의는 이제 지겹다",
        "url": "https://webtoon.kakao.com/content/책빙의는-이제-지겹다/3140",
        "thumb": "https://kr-a.kakaopagecdn.com/P/C/3140/bg/1x/e962ddc2-e098-4ecf-9cfd-2ff6092ee63b.webp",
        "platform": "kakao",
        "day": "sat",
        "dayLabel": "토"
      },
      {
        "title": "통각 설정 꺼놨다니까요",
        "url": "https://webtoon.kakao.com/content/통각-설정-꺼놨다니까요/4126",
        "thumb": "https://kr-a.kakaopagecdn.com/P/C/4126/bg/1x/493e627d-880a-4a9d-af84-6f9fb0700110.webp",
        "platform": "kakao",
        "day": "sat",
        "dayLabel": "토"
      },
      {
        "title": "남편의 말대로 정부를 들였다",
        "url": "https://webtoon.kakao.com/content/남편의-말대로-정부를-들였다/3816",
        "thumb": "https://kr-a.kakaopagecdn.com/P/C/3816/bg/1x/0845b14e-1ab0-4c8b-88f1-155d304bb182.webp",
        "platform": "kakao",
        "day": "sat",
        "dayLabel": "토"
      },
      {
        "title": "체육교사 김계란",
        "url": "https://webtoon.kakao.com/content/체육교사-김계란/4835",
        "thumb": "https://kr-a.kakaopagecdn.com/P/C/4835/bg/1x/3c2f2669-965a-409b-a5dc-620b1d515979.webp",
        "platform": "kakao",
        "day": "sat",
        "dayLabel": "토"
      },
      {
        "title": "계약 결혼을 완벽하게 끝내는 방법",
        "url": "https://webtoon.kakao.com/content/계약-결혼을-완벽하게-끝내는-방법/4176",
        "thumb": "https://kr-a.kakaopagecdn.com/P/C/4176/bg/1x/add0d5ff-658d-4478-beab-6b2af81d2b27.webp",
        "platform": "kakao",
        "day": "sat",
        "dayLabel": "토"
      },
      {
        "title": "대표님과 위장 가족이 되었습니다",
        "url": "https://webtoon.kakao.com/content/대표님과-위장-가족이-되었습니다/4116",
        "thumb": "https://kr-a.kakaopagecdn.com/P/C/4116/bg/1x/12b96b3d-fc35-44d2-b9fe-21174e645014.webp",
        "platform": "kakao",
        "day": "sat",
        "dayLabel": "토"
      },
      {
        "title": "그래서 아내는 누가 죽인 건데",
        "url": "https://webtoon.kakao.com/content/그래서-아내는-누가-죽인-건데/4228",
        "thumb": "https://kr-a.kakaopagecdn.com/P/C/4228/bg/1x/1fa06445-0ffa-47d7-8a02-d89ef34379e1.webp",
        "platform": "kakao",
        "day": "sat",
        "dayLabel": "토"
      },
      {
        "title": "악역에 빙의했지만 고양이나 키울래요",
        "url": "https://webtoon.kakao.com/content/악역에-빙의했지만-고양이나-키울래요/4115",
        "thumb": "https://kr-a.kakaopagecdn.com/P/C/4115/bg/1x/667c1ee0-a5ba-4466-ae6b-e856ecc2c70c.webp",
        "platform": "kakao",
        "day": "sat",
        "dayLabel": "토"
      },
      {
        "title": "진혼기",
        "url": "https://webtoon.kakao.com/content/진혼기/4230",
        "thumb": "https://kr-a.kakaopagecdn.com/P/C/4230/bg/1x/ab62b9ad-c562-4f8c-9a96-b7ba7637d08d.webp",
        "platform": "kakao",
        "day": "sat",
        "dayLabel": "토"
      },
      {
        "title": "인간의 딸이 되었다",
        "url": "https://webtoon.kakao.com/content/인간의-딸이-되었다/4485",
        "thumb": "https://kr-a.kakaopagecdn.com/P/C/4485/bg/1x/879a5a91-2682-40a2-99be-ab55300bde25.webp",
        "platform": "kakao",
        "day": "sat",
        "dayLabel": "토"
      },
      {
        "title": "돈으로 약혼자를 키웠습니다",
        "url": "https://webtoon.kakao.com/content/돈으로-약혼자를-키웠습니다/3891",
        "thumb": "https://kr-a.kakaopagecdn.com/P/C/3891/bg/1x/a7cb04e0-2bb7-4872-b4e7-5bc8500e964a.webp",
        "platform": "kakao",
        "day": "sat",
        "dayLabel": "토"
      },
      {
        "title": "신데렐라는 이 멧밭쥐가 데려갑니다",
        "url": "https://webtoon.kakao.com/content/신데렐라는-이-멧밭쥐가-데려갑니다/4525",
        "thumb": "https://kr-a.kakaopagecdn.com/P/C/4525/bg/1x/cd9a24bc-8789-4caa-923b-9ae8b1d86459.webp",
        "platform": "kakao",
        "day": "sat",
        "dayLabel": "토"
      },
      {
        "title": "99대장",
        "url": "https://webtoon.kakao.com/content/99대장/3862",
        "thumb": "https://kr-a.kakaopagecdn.com/P/C/3862/bg/1x/bacd7f80-b814-4db1-a99d-af678db054f4.webp",
        "platform": "kakao",
        "day": "sat",
        "dayLabel": "토"
      },
      {
        "title": "주인공들의 아이로 태어났다",
        "url": "https://webtoon.kakao.com/content/주인공들의-아이로-태어났다/3296",
        "thumb": "https://kr-a.kakaopagecdn.com/P/C/3296/bg/1x/282ddf8a-c8f8-49f8-b009-a7f31c8f402b.webp",
        "platform": "kakao",
        "day": "sat",
        "dayLabel": "토"
      },
      {
        "title": "극락왕생",
        "url": "https://webtoon.kakao.com/content/극락왕생/2680",
        "thumb": "https://kr-a.kakaopagecdn.com/P/C/2680/bg/1x/6733f7d3-ebfa-4a2b-9c12-7a07a240ab33.webp",
        "platform": "kakao",
        "day": "sat",
        "dayLabel": "토"
      },
      {
        "title": "다크 히어로의 딸이 되는 법",
        "url": "https://webtoon.kakao.com/content/다크-히어로의-딸이-되는-법/2541",
        "thumb": "https://kr-a.kakaopagecdn.com/P/C/2541/bg/1x/26576827-1baa-408a-a104-b10097717e6f.webp",
        "platform": "kakao",
        "day": "sat",
        "dayLabel": "토"
      },
      {
        "title": "마음이 이끄는 대로",
        "url": "https://webtoon.kakao.com/content/마음이-이끄는-대로/4190",
        "thumb": "https://kr-a.kakaopagecdn.com/P/C/4190/bg/1x/88c5d360-b818-45fa-9308-1bd5882c6dcb.webp",
        "platform": "kakao",
        "day": "sat",
        "dayLabel": "토"
      },
      {
        "title": "몰락한 명가의 플레이어",
        "url": "https://webtoon.kakao.com/content/몰락한-명가의-플레이어/4684",
        "thumb": "https://kr-a.kakaopagecdn.com/P/C/4684/bg/1x/c413a430-f233-4bcd-91cb-345e82902137.webp",
        "platform": "kakao",
        "day": "sat",
        "dayLabel": "토"
      },
      {
        "title": "내 남편이 너무 귀여워서 곤란하다",
        "url": "https://webtoon.kakao.com/content/내-남편이-너무-귀여워서-곤란하다/2620",
        "thumb": "https://kr-a.kakaopagecdn.com/P/C/2620/bg/1x/0eca3274-e564-4375-b554-244e2e578cc0.webp",
        "platform": "kakao",
        "day": "sat",
        "dayLabel": "토"
      },
      {
        "title": "하프블러드",
        "url": "https://webtoon.kakao.com/content/하프블러드/4635",
        "thumb": "https://kr-a.kakaopagecdn.com/P/C/4635/bg/1x/8f6d270d-3a5d-4cab-9f4b-677104904cba.webp",
        "platform": "kakao",
        "day": "sat",
        "dayLabel": "토"
      },
      {
        "title": "게임 속 기연이 현실로",
        "url": "https://webtoon.kakao.com/content/게임-속-기연이-현실로/3715",
        "thumb": "https://kr-a.kakaopagecdn.com/P/C/3715/bg/1x/2883579d-75f9-4b8a-950d-46b808d08faf.webp",
        "platform": "kakao",
        "day": "sat",
        "dayLabel": "토"
      },
      {
        "title": "백작가의 사랑받는 작은 주인님",
        "url": "https://webtoon.kakao.com/content/백작가의-사랑받는-작은-주인님/4688",
        "thumb": "https://kr-a.kakaopagecdn.com/P/C/4688/bg/1x/2f0571fb-08f8-482a-9c85-e5c72b18559d.webp",
        "platform": "kakao",
        "day": "sat",
        "dayLabel": "토"
      },
      {
        "title": "이혼 전략",
        "url": "https://webtoon.kakao.com/content/이혼-전략/4104",
        "thumb": "https://kr-a.kakaopagecdn.com/P/C/4104/bg/1x/3833bcdf-4b0d-47e4-b16d-44a15b573e41.webp",
        "platform": "kakao",
        "day": "sat",
        "dayLabel": "토"
      },
      {
        "title": "최강자 오빠가 기억을 잃었다",
        "url": "https://webtoon.kakao.com/content/최강자-오빠가-기억을-잃었다/4389",
        "thumb": "https://kr-a.kakaopagecdn.com/P/C/4389/bg/1x/f792b2b2-abb3-4ab3-a1bb-d22158662270.webp",
        "platform": "kakao",
        "day": "sat",
        "dayLabel": "토"
      },
      {
        "title": "내게 집착하세요",
        "url": "https://webtoon.kakao.com/content/내게-집착하세요/4234",
        "thumb": "https://kr-a.kakaopagecdn.com/P/C/4234/bg/1x/8a4a5a50-0656-4166-aa38-cc8f4ef3311a.webp",
        "platform": "kakao",
        "day": "sat",
        "dayLabel": "토"
      },
      {
        "title": "도사 아카데미 무위관",
        "url": "https://webtoon.kakao.com/content/도사-아카데미-무위관/3850",
        "thumb": "https://kr-a.kakaopagecdn.com/P/C/3850/bg/1x/eebebd4f-b3c5-4c59-b144-0d4808feb0b4.webp",
        "platform": "kakao",
        "day": "sat",
        "dayLabel": "토"
      },
      {
        "title": "엑스트라지만 공작 외동딸",
        "url": "https://webtoon.kakao.com/content/엑스트라지만-공작-외동딸/4331",
        "thumb": "https://kr-a.kakaopagecdn.com/P/C/4331/bg/1x/aa92fe4a-a63a-4a48-a234-7c56ea3a0169.webp",
        "platform": "kakao",
        "day": "sat",
        "dayLabel": "토"
      },
      {
        "title": "골든 프린트",
        "url": "https://webtoon.kakao.com/content/골든-프린트/3109",
        "thumb": "https://kr-a.kakaopagecdn.com/P/C/3109/bg/1x/716979b2-148b-4673-98a3-9ad1657801ca.webp",
        "platform": "kakao",
        "day": "sat",
        "dayLabel": "토"
      },
      {
        "title": "망겜 속에 갇혔다",
        "url": "https://webtoon.kakao.com/content/망겜-속에-갇혔다/3640",
        "thumb": "https://kr-a.kakaopagecdn.com/P/C/3640/bg/1x/ededf5c4-f794-4f90-9fff-58ac3ffba1e3.webp",
        "platform": "kakao",
        "day": "sat",
        "dayLabel": "토"
      },
      {
        "title": "샤이닝 썸머",
        "url": "https://webtoon.kakao.com/content/샤이닝-썸머/3749",
        "thumb": "https://kr-a.kakaopagecdn.com/P/C/3749/bg/1x/d7474f97-5145-4096-9f0b-fc932feb5780.webp",
        "platform": "kakao",
        "day": "sat",
        "dayLabel": "토"
      },
      {
        "title": "콜사인",
        "url": "https://webtoon.kakao.com/content/콜사인/2682",
        "thumb": "https://kr-a.kakaopagecdn.com/P/C/2682/bg/1x/5fd6aa8d-19d6-433b-9fd1-dfbf2dfcc640.webp",
        "platform": "kakao",
        "day": "sat",
        "dayLabel": "토"
      },
      {
        "title": "불멸낭인",
        "url": "https://webtoon.kakao.com/content/불멸낭인/4363",
        "thumb": "https://kr-a.kakaopagecdn.com/P/C/4363/bg/1x/823423a1-5493-4c1d-aba4-1d4d49605487.webp",
        "platform": "kakao",
        "day": "sat",
        "dayLabel": "토"
      },
      {
        "title": "메모라이즈MEMORIZE",
        "url": "https://webtoon.kakao.com/content/메모라이즈MEMORIZE/2866",
        "thumb": "https://kr-a.kakaopagecdn.com/P/C/2866/bg/1x/3d35aa91-76b8-4506-8f22-70f61ea12ade.webp",
        "platform": "kakao",
        "day": "sat",
        "dayLabel": "토"
      },
      {
        "title": "새 남편을 구합니다",
        "url": "https://webtoon.kakao.com/content/새-남편을-구합니다/4253",
        "thumb": "https://kr-a.kakaopagecdn.com/P/C/4253/bg/1x/4adf6647-fd3e-457a-8654-5f4af72b41da.webp",
        "platform": "kakao",
        "day": "sat",
        "dayLabel": "토"
      },
      {
        "title": "우리 악녀님이 달라졌어요",
        "url": "https://webtoon.kakao.com/content/우리-악녀님이-달라졌어요/4269",
        "thumb": "https://kr-a.kakaopagecdn.com/P/C/4269/bg/1x/62b9bb6e-563e-4a36-a92f-a410d99481dd.webp",
        "platform": "kakao",
        "day": "sat",
        "dayLabel": "토"
      },
      {
        "title": "갑질하는 영주님",
        "url": "https://webtoon.kakao.com/content/갑질하는-영주님/2850",
        "thumb": "https://kr-a.kakaopagecdn.com/P/C/2850/bg/1x/245ddb8a-86ab-4461-bd1f-2c90f7a6c9f0.webp",
        "platform": "kakao",
        "day": "sat",
        "dayLabel": "토"
      },
      {
        "title": "괴공유록",
        "url": "https://webtoon.kakao.com/content/괴공유록/4068",
        "thumb": "https://kr-a.kakaopagecdn.com/P/C/4068/bg/1x/d975d202-357d-4244-9a46-ce31345de47c.webp",
        "platform": "kakao",
        "day": "sat",
        "dayLabel": "토"
      },
      {
        "title": "캐스팅 신데렐라",
        "url": "https://webtoon.kakao.com/content/캐스팅-신데렐라/4459",
        "thumb": "https://kr-a.kakaopagecdn.com/P/C/4459/bg/1x/fb412a10-419c-4b2a-bdd4-84cb3f2c6382.webp",
        "platform": "kakao",
        "day": "sat",
        "dayLabel": "토"
      },
      {
        "title": "내게 미친 세계관 최강자를 조심할 것",
        "url": "https://webtoon.kakao.com/content/내게-미친-세계관-최강자를-조심할-것/4240",
        "thumb": "https://kr-a.kakaopagecdn.com/P/C/4240/bg/1x/f25ad829-684d-4298-abf0-c07c7560ec01.webp",
        "platform": "kakao",
        "day": "sat",
        "dayLabel": "토"
      },
      {
        "title": "나는 황제의 잃어버린 딸",
        "url": "https://webtoon.kakao.com/content/나는-황제의-잃어버린-딸/4010",
        "thumb": "https://kr-a.kakaopagecdn.com/P/C/4010/bg/1x/0d6c1514-fe09-439d-815f-8ce5789966dd.webp",
        "platform": "kakao",
        "day": "sat",
        "dayLabel": "토"
      },
      {
        "title": "약먹는 천재마법사",
        "url": "https://webtoon.kakao.com/content/약먹는-천재마법사/3357",
        "thumb": "https://kr-a.kakaopagecdn.com/P/C/3357/bg/1x/e4e11f43-3557-47af-8d2a-a853cfd32a60.webp",
        "platform": "kakao",
        "day": "sat",
        "dayLabel": "토"
      },
      {
        "title": "위아영",
        "url": "https://webtoon.kakao.com/content/위아영/4229",
        "thumb": "https://kr-a.kakaopagecdn.com/P/C/4229/bg/1x/19cd41c7-0681-4da3-9508-013480eac80f.webp",
        "platform": "kakao",
        "day": "sat",
        "dayLabel": "토"
      },
      {
        "title": "악녀들을 위한 안내서",
        "url": "https://webtoon.kakao.com/content/악녀들을-위한-안내서/3748",
        "thumb": "https://kr-a.kakaopagecdn.com/P/C/3748/bg/1x/86d2f355-c90d-4605-abb4-e93a0210cd3a.webp",
        "platform": "kakao",
        "day": "sat",
        "dayLabel": "토"
      },
      {
        "title": "계급장 떼고 결혼합니다",
        "url": "https://webtoon.kakao.com/content/계급장-떼고-결혼합니다/4227",
        "thumb": "https://kr-a.kakaopagecdn.com/P/C/4227/bg/1x/7570c946-5da5-4de5-8736-59dd033bf1e9.webp",
        "platform": "kakao",
        "day": "sat",
        "dayLabel": "토"
      },
      {
        "title": "100마일",
        "url": "https://webtoon.kakao.com/content/100마일/3538",
        "thumb": "https://kr-a.kakaopagecdn.com/P/C/3538/bg/1x/2b94694a-891b-436d-8f8f-1f87b6ca171f.webp",
        "platform": "kakao",
        "day": "sat",
        "dayLabel": "토"
      },
      {
        "title": "사내 연애 전선",
        "url": "https://webtoon.kakao.com/content/사내-연애-전선/4050",
        "thumb": "https://kr-a.kakaopagecdn.com/P/C/4050/bg/1x/e7355a94-4d7c-47dd-bf9c-bb9fd9ae1b07.webp",
        "platform": "kakao",
        "day": "sat",
        "dayLabel": "토"
      },
      {
        "title": "그가 죽여야 할 최종 악녀가 저랍니다",
        "url": "https://webtoon.kakao.com/content/그가-죽여야-할-최종-악녀가-저랍니다/4320",
        "thumb": "https://kr-a.kakaopagecdn.com/P/C/4320/bg/1x/b3e844f5-f20e-4d29-aae6-3e7436628fbd.webp",
        "platform": "kakao",
        "day": "sat",
        "dayLabel": "토"
      },
      {
        "title": "조선야설",
        "url": "https://webtoon.kakao.com/content/조선야설/4219",
        "thumb": "https://kr-a.kakaopagecdn.com/P/C/4219/bg/1x/0f57526f-568e-4440-b74e-b72f70aaef33.webp",
        "platform": "kakao",
        "day": "sat",
        "dayLabel": "토"
      },
      {
        "title": "천사혈성",
        "url": "https://webtoon.kakao.com/content/천사혈성/4018",
        "thumb": "https://kr-a.kakaopagecdn.com/P/C/4018/bg/1x/0cbd601e-83e0-4926-bf3c-282c62cd1640.webp",
        "platform": "kakao",
        "day": "sat",
        "dayLabel": "토"
      },
      {
        "title": "이제 그만 새가족을 찾으려합니다",
        "url": "https://webtoon.kakao.com/content/이제-그만-새가족을-찾으려합니다/3615",
        "thumb": "https://kr-a.kakaopagecdn.com/P/C/3615/bg/1x/fee77767-c657-4d85-b1bc-f3f73b99332c.webp",
        "platform": "kakao",
        "day": "sat",
        "dayLabel": "토"
      },
      {
        "title": "응급 사랑으로 치료하는 방법",
        "url": "https://webtoon.kakao.com/content/응급-사랑으로-치료하는-방법/3762",
        "thumb": "https://kr-a.kakaopagecdn.com/P/C/3762/bg/1x/e5d1110d-ecce-45b5-87d9-738dfc4686df.webp",
        "platform": "kakao",
        "day": "sat",
        "dayLabel": "토"
      },
      {
        "title": "무패의 랭커",
        "url": "https://webtoon.kakao.com/content/무패의-랭커/2807",
        "thumb": "https://kr-a.kakaopagecdn.com/P/C/2807/bg/1x/6a1ce6ff-fc6f-4978-ac1b-1b852bb4e7e2.webp",
        "platform": "kakao",
        "day": "sat",
        "dayLabel": "토"
      },
      {
        "title": "나는 회귀자가 아닙니다",
        "url": "https://webtoon.kakao.com/content/나는-회귀자가-아닙니다/3837",
        "thumb": "https://kr-a.kakaopagecdn.com/P/C/3837/bg/1x/35a8be05-b5a0-4f7c-8690-2a2ce0b24f10.webp",
        "platform": "kakao",
        "day": "sat",
        "dayLabel": "토"
      },
      {
        "title": "소설 속 막내황자가 되었다",
        "url": "https://webtoon.kakao.com/content/소설-속-막내황자가-되었다/3877",
        "thumb": "https://kr-a.kakaopagecdn.com/P/C/3877/bg/1x/03d77828-2281-49c2-8619-c9bac3cdf350.webp",
        "platform": "kakao",
        "day": "sat",
        "dayLabel": "토"
      },
      {
        "title": "코스모의 미로",
        "url": "https://webtoon.kakao.com/content/코스모의-미로/3901",
        "thumb": "https://kr-a.kakaopagecdn.com/P/C/3901/bg/1x/d8437c27-5d69-4a73-b9b9-9de3bd4ef379.webp",
        "platform": "kakao",
        "day": "sat",
        "dayLabel": "토"
      },
      {
        "title": "12시의 마리오네트",
        "url": "https://webtoon.kakao.com/content/12시의-마리오네트/3743",
        "thumb": "https://kr-a.kakaopagecdn.com/P/C/3743/bg/1x/f1037ae6-06cb-4738-b92e-ec289988d50c.webp",
        "platform": "kakao",
        "day": "sat",
        "dayLabel": "토"
      },
      {
        "title": "악역을 위한 메르헨",
        "url": "https://webtoon.kakao.com/content/악역을-위한-메르헨/3874",
        "thumb": "https://kr-a.kakaopagecdn.com/P/C/3874/bg/1x/79adb615-6928-43bf-88e2-eb058e279f94.webp",
        "platform": "kakao",
        "day": "sat",
        "dayLabel": "토"
      },
      {
        "title": "결혼적령기 무림교관",
        "url": "https://webtoon.kakao.com/content/결혼적령기-무림교관/4026",
        "thumb": "https://kr-a.kakaopagecdn.com/P/C/4026/bg/1x/0de36cc6-9bfb-4884-a1f9-3902c73dd631.webp",
        "platform": "kakao",
        "day": "sat",
        "dayLabel": "토"
      },
      {
        "title": "아크 더 레전드",
        "url": "https://webtoon.kakao.com/content/아크-더-레전드/3173",
        "thumb": "https://kr-a.kakaopagecdn.com/P/C/3173/bg/1x/409bdfdd-17c8-45e1-9227-c671f269b5de.webp",
        "platform": "kakao",
        "day": "sat",
        "dayLabel": "토"
      }
    ],
    "sun": []
  }
}